uno_oauth_mcp/__init__.py
uno_oauth_mcp/fastmcp.py
uno_oauth_mcp/lowlevel.py
uno_oauth_mcp/settings.py
uno_oauth_mcp/verifier.py
uno_oauth_mcp-0.1.0.dist-info/METADATA
uno_oauth_mcp-0.1.0.dist-info/WHEEL
uno_oauth_mcp-0.1.0.dist-info/RECORD
