Metadata-Version: 2.4
Name: uno-oauth-mcp
Version: 0.1.0
Summary: Uno OAuth MCP - 让 MCP Server 快速接入 mcpmarket.cn OAuth 认证
Project-URL: Homepage, https://github.com/xray918/uno-oauth-mcp
Project-URL: Documentation, https://mcpmarket.cn/docs/uno-oauth-mcp
Project-URL: Repository, https://github.com/xray918/uno-oauth-mcp
Author-email: MCPMarket <support@mcpmarket.cn>
License: MIT
Keywords: authentication,mcp,mcpmarket,oauth,uno
Classifier: Development Status :: 4 - Beta
Classifier: Framework :: AsyncIO
Classifier: Intended Audience :: Developers
Classifier: License :: OSI Approved :: MIT License
Classifier: Programming Language :: Python :: 3
Classifier: Programming Language :: Python :: 3.10
Classifier: Programming Language :: Python :: 3.11
Classifier: Programming Language :: Python :: 3.12
Classifier: Topic :: Security
Requires-Python: >=3.10
Requires-Dist: httpx>=0.27.0
Requires-Dist: mcp>=1.0.0
Provides-Extra: dev
Requires-Dist: black; extra == 'dev'
Requires-Dist: isort; extra == 'dev'
Requires-Dist: mypy; extra == 'dev'
Requires-Dist: pytest-asyncio>=0.21.0; extra == 'dev'
Requires-Dist: pytest>=7.0.0; extra == 'dev'
